pynotator/Pynotator.py
pynotator/__init__.py
pynotator-0.0.3.dist-info/METADATA
pynotator-0.0.3.dist-info/WHEEL
pynotator-0.0.3.dist-info/top_level.txt
pynotator-0.0.3.dist-info/RECORD
